{"type":"PR","pr":{"number":19,"head":"de2797ff50e14f2b9f565011a6a19a47c5b01d90"},"user":"Mary Warrington","status":"draft","branch":"cms/photography-guidelines","collection":"docs","title":"Photography Guidelines","description":"No Description!","objects":{"entry":{"path":"docs/photography-guidelines.md","sha":"dd3284b9835d656bf5da085c74975cc06d6b0e1b"},"files":[{"path":"/public/uploads/photog-examples.png","sha":"e7976932c9fccfb3dac1a360113a669d073953b8"}]},"timeStamp":"2018-12-17T16:16:47.993Z"}